[
  {
    "date": "16_7_2552",
    "award_type": "firstAward",
    "number": "000816"
  },
  {
    "date": "16_7_2552",
    "award_type": "three_prefix",
    "number": ""
  },
  {
    "date": "16_7_2552",
    "award_type": "three_suffix",
    "number": "005"
  },
  {
    "date": "16_7_2552",
    "award_type": "three_suffix",
    "number": "177"
  },
  {
    "date": "16_7_2552",
    "award_type": "three_suffix",
    "number": "356"
  },
  {
    "date": "16_7_2552",
    "award_type": "three_suffix",
    "number": "836"
  },
  {
    "date": "16_7_2552",
    "award_type": "two_suffix",
    "number": "94"
  },
  {
    "date": "16_7_2552",
    "award_type": "secondAward",
    "number": "169964"
  },
  {
    "date": "16_7_2552",
    "award_type": "secondAward",
    "number": "292125"
  },
  {
    "date": "16_7_2552",
    "award_type": "secondAward",
    "number": "373983"
  },
  {
    "date": "16_7_2552",
    "award_type": "secondAward",
    "number": "533197"
  },
  {
    "date": "16_7_2552",
    "award_type": "secondAward",
    "number": "944511"
  },
  {
    "date": "16_7_2552",
    "award_type": "thirdAward",
    "number": "082354"
  },
  {
    "date": "16_7_2552",
    "award_type": "thirdAward",
    "number": "261753"
  },
  {
    "date": "16_7_2552",
    "award_type": "thirdAward",
    "number": "510745"
  },
  {
    "date": "16_7_2552",
    "award_type": "thirdAward",
    "number": "692173"
  },
  {
    "date": "16_7_2552",
    "award_type": "thirdAward",
    "number": "792039"
  },
  {
    "date": "16_7_2552",
    "award_type": "thirdAward",
    "number": "805155"
  },
  {
    "date": "16_7_2552",
    "award_type": "thirdAward",
    "number": "866501"
  },
  {
    "date": "16_7_2552",
    "award_type": "thirdAward",
    "number": "930331"
  },
  {
    "date": "16_7_2552",
    "award_type": "thirdAward",
    "number": "943298"
  },
  {
    "date": "16_7_2552",
    "award_type": "thirdAward",
    "number": "981253"
  },
  {
    "date": "16_7_2552",
    "award_type": "fourthAward",
    "number": "008837"
  },
  {
    "date": "16_7_2552",
    "award_type": "fourthAward",
    "number": "036184"
  },
  {
    "date": "16_7_2552",
    "award_type": "fourthAward",
    "number": "037821"
  },
  {
    "date": "16_7_2552",
    "award_type": "fourthAward",
    "number": "085420"
  },
  {
    "date": "16_7_2552",
    "award_type": "fourthAward",
    "number": "165019"
  },
  {
    "date": "16_7_2552",
    "award_type": "fourthAward",
    "number": "165512"
  },
  {
    "date": "16_7_2552",
    "award_type": "fourthAward",
    "number": "187110"
  },
  {
    "date": "16_7_2552",
    "award_type": "fourthAward",
    "number": "191200"
  },
  {
    "date": "16_7_2552",
    "award_type": "fourthAward",
    "number": "194142"
  },
  {
    "date": "16_7_2552",
    "award_type": "fourthAward",
    "number": "195492"
  },
  {
    "date": "16_7_2552",
    "award_type": "fourthAward",
    "number": "222653"
  },
  {
    "date": "16_7_2552",
    "award_type": "fourthAward",
    "number": "234097"
  },
  {
    "date": "16_7_2552",
    "award_type": "fourthAward",
    "number": "241565"
  },
  {
    "date": "16_7_2552",
    "award_type": "fourthAward",
    "number": "252275"
  },
  {
    "date": "16_7_2552",
    "award_type": "fourthAward",
    "number": "276987"
  },
  {
    "date": "16_7_2552",
    "award_type": "fourthAward",
    "number": "291522"
  },
  {
    "date": "16_7_2552",
    "award_type": "fourthAward",
    "number": "315259"
  },
  {
    "date": "16_7_2552",
    "award_type": "fourthAward",
    "number": "318365"
  },
  {
    "date": "16_7_2552",
    "award_type": "fourthAward",
    "number": "324019"
  },
  {
    "date": "16_7_2552",
    "award_type": "fourthAward",
    "number": "332537"
  },
  {
    "date": "16_7_2552",
    "award_type": "fourthAward",
    "number": "392298"
  },
  {
    "date": "16_7_2552",
    "award_type": "fourthAward",
    "number": "472199"
  },
  {
    "date": "16_7_2552",
    "award_type": "fourthAward",
    "number": "474072"
  },
  {
    "date": "16_7_2552",
    "award_type": "fourthAward",
    "number": "474425"
  },
  {
    "date": "16_7_2552",
    "award_type": "fourthAward",
    "number": "477518"
  },
  {
    "date": "16_7_2552",
    "award_type": "fourthAward",
    "number": "488339"
  },
  {
    "date": "16_7_2552",
    "award_type": "fourthAward",
    "number": "490220"
  },
  {
    "date": "16_7_2552",
    "award_type": "fourthAward",
    "number": "492112"
  },
  {
    "date": "16_7_2552",
    "award_type": "fourthAward",
    "number": "511487"
  },
  {
    "date": "16_7_2552",
    "award_type": "fourthAward",
    "number": "568958"
  },
  {
    "date": "16_7_2552",
    "award_type": "fourthAward",
    "number": "600917"
  },
  {
    "date": "16_7_2552",
    "award_type": "fourthAward",
    "number": "601409"
  },
  {
    "date": "16_7_2552",
    "award_type": "fourthAward",
    "number": "635607"
  },
  {
    "date": "16_7_2552",
    "award_type": "fourthAward",
    "number": "641501"
  },
  {
    "date": "16_7_2552",
    "award_type": "fourthAward",
    "number": "659611"
  },
  {
    "date": "16_7_2552",
    "award_type": "fourthAward",
    "number": "724932"
  },
  {
    "date": "16_7_2552",
    "award_type": "fourthAward",
    "number": "727376"
  },
  {
    "date": "16_7_2552",
    "award_type": "fourthAward",
    "number": "738005"
  },
  {
    "date": "16_7_2552",
    "award_type": "fourthAward",
    "number": "760339"
  },
  {
    "date": "16_7_2552",
    "award_type": "fourthAward",
    "number": "784534"
  },
  {
    "date": "16_7_2552",
    "award_type": "fourthAward",
    "number": "830421"
  },
  {
    "date": "16_7_2552",
    "award_type": "fourthAward",
    "number": "840504"
  },
  {
    "date": "16_7_2552",
    "award_type": "fourthAward",
    "number": "848138"
  },
  {
    "date": "16_7_2552",
    "award_type": "fourthAward",
    "number": "903730"
  },
  {
    "date": "16_7_2552",
    "award_type": "fourthAward",
    "number": "921590"
  },
  {
    "date": "16_7_2552",
    "award_type": "fourthAward",
    "number": "921885"
  },
  {
    "date": "16_7_2552",
    "award_type": "fourthAward",
    "number": "923059"
  },
  {
    "date": "16_7_2552",
    "award_type": "fourthAward",
    "number": "939234"
  },
  {
    "date": "16_7_2552",
    "award_type": "fourthAward",
    "number": "958699"
  },
  {
    "date": "16_7_2552",
    "award_type": "fourthAward",
    "number": "958853"
  },
  {
    "date": "16_7_2552",
    "award_type": "fifthAward",
    "number": "019215"
  },
  {
    "date": "16_7_2552",
    "award_type": "fifthAward",
    "number": "022920"
  },
  {
    "date": "16_7_2552",
    "award_type": "fifthAward",
    "number": "032261"
  },
  {
    "date": "16_7_2552",
    "award_type": "fifthAward",
    "number": "034041"
  },
  {
    "date": "16_7_2552",
    "award_type": "fifthAward",
    "number": "041287"
  },
  {
    "date": "16_7_2552",
    "award_type": "fifthAward",
    "number": "047118"
  },
  {
    "date": "16_7_2552",
    "award_type": "fifthAward",
    "number": "048143"
  },
  {
    "date": "16_7_2552",
    "award_type": "fifthAward",
    "number": "053587"
  },
  {
    "date": "16_7_2552",
    "award_type": "fifthAward",
    "number": "059853"
  },
  {
    "date": "16_7_2552",
    "award_type": "fifthAward",
    "number": "069210"
  },
  {
    "date": "16_7_2552",
    "award_type": "fifthAward",
    "number": "076200"
  },
  {
    "date": "16_7_2552",
    "award_type": "fifthAward",
    "number": "078965"
  },
  {
    "date": "16_7_2552",
    "award_type": "fifthAward",
    "number": "112020"
  },
  {
    "date": "16_7_2552",
    "award_type": "fifthAward",
    "number": "144504"
  },
  {
    "date": "16_7_2552",
    "award_type": "fifthAward",
    "number": "147083"
  },
  {
    "date": "16_7_2552",
    "award_type": "fifthAward",
    "number": "152307"
  },
  {
    "date": "16_7_2552",
    "award_type": "fifthAward",
    "number": "157581"
  },
  {
    "date": "16_7_2552",
    "award_type": "fifthAward",
    "number": "169677"
  },
  {
    "date": "16_7_2552",
    "award_type": "fifthAward",
    "number": "175370"
  },
  {
    "date": "16_7_2552",
    "award_type": "fifthAward",
    "number": "185747"
  },
  {
    "date": "16_7_2552",
    "award_type": "fifthAward",
    "number": "189553"
  },
  {
    "date": "16_7_2552",
    "award_type": "fifthAward",
    "number": "192651"
  },
  {
    "date": "16_7_2552",
    "award_type": "fifthAward",
    "number": "195236"
  },
  {
    "date": "16_7_2552",
    "award_type": "fifthAward",
    "number": "198946"
  },
  {
    "date": "16_7_2552",
    "award_type": "fifthAward",
    "number": "221823"
  },
  {
    "date": "16_7_2552",
    "award_type": "fifthAward",
    "number": "231231"
  },
  {
    "date": "16_7_2552",
    "award_type": "fifthAward",
    "number": "232322"
  },
  {
    "date": "16_7_2552",
    "award_type": "fifthAward",
    "number": "233416"
  },
  {
    "date": "16_7_2552",
    "award_type": "fifthAward",
    "number": "233560"
  },
  {
    "date": "16_7_2552",
    "award_type": "fifthAward",
    "number": "246958"
  },
  {
    "date": "16_7_2552",
    "award_type": "fifthAward",
    "number": "250933"
  },
  {
    "date": "16_7_2552",
    "award_type": "fifthAward",
    "number": "256442"
  },
  {
    "date": "16_7_2552",
    "award_type": "fifthAward",
    "number": "256943"
  },
  {
    "date": "16_7_2552",
    "award_type": "fifthAward",
    "number": "293606"
  },
  {
    "date": "16_7_2552",
    "award_type": "fifthAward",
    "number": "313211"
  },
  {
    "date": "16_7_2552",
    "award_type": "fifthAward",
    "number": "317394"
  },
  {
    "date": "16_7_2552",
    "award_type": "fifthAward",
    "number": "323706"
  },
  {
    "date": "16_7_2552",
    "award_type": "fifthAward",
    "number": "342122"
  },
  {
    "date": "16_7_2552",
    "award_type": "fifthAward",
    "number": "347370"
  },
  {
    "date": "16_7_2552",
    "award_type": "fifthAward",
    "number": "357344"
  },
  {
    "date": "16_7_2552",
    "award_type": "fifthAward",
    "number": "358960"
  },
  {
    "date": "16_7_2552",
    "award_type": "fifthAward",
    "number": "373690"
  },
  {
    "date": "16_7_2552",
    "award_type": "fifthAward",
    "number": "377513"
  },
  {
    "date": "16_7_2552",
    "award_type": "fifthAward",
    "number": "378689"
  },
  {
    "date": "16_7_2552",
    "award_type": "fifthAward",
    "number": "385851"
  },
  {
    "date": "16_7_2552",
    "award_type": "fifthAward",
    "number": "392585"
  },
  {
    "date": "16_7_2552",
    "award_type": "fifthAward",
    "number": "407348"
  },
  {
    "date": "16_7_2552",
    "award_type": "fifthAward",
    "number": "407740"
  },
  {
    "date": "16_7_2552",
    "award_type": "fifthAward",
    "number": "413562"
  },
  {
    "date": "16_7_2552",
    "award_type": "fifthAward",
    "number": "423682"
  },
  {
    "date": "16_7_2552",
    "award_type": "fifthAward",
    "number": "450080"
  },
  {
    "date": "16_7_2552",
    "award_type": "fifthAward",
    "number": "463197"
  },
  {
    "date": "16_7_2552",
    "award_type": "fifthAward",
    "number": "482119"
  },
  {
    "date": "16_7_2552",
    "award_type": "fifthAward",
    "number": "490242"
  },
  {
    "date": "16_7_2552",
    "award_type": "fifthAward",
    "number": "503831"
  },
  {
    "date": "16_7_2552",
    "award_type": "fifthAward",
    "number": "522240"
  },
  {
    "date": "16_7_2552",
    "award_type": "fifthAward",
    "number": "529840"
  },
  {
    "date": "16_7_2552",
    "award_type": "fifthAward",
    "number": "542009"
  },
  {
    "date": "16_7_2552",
    "award_type": "fifthAward",
    "number": "543772"
  },
  {
    "date": "16_7_2552",
    "award_type": "fifthAward",
    "number": "552719"
  },
  {
    "date": "16_7_2552",
    "award_type": "fifthAward",
    "number": "558203"
  },
  {
    "date": "16_7_2552",
    "award_type": "fifthAward",
    "number": "576454"
  },
  {
    "date": "16_7_2552",
    "award_type": "fifthAward",
    "number": "577208"
  },
  {
    "date": "16_7_2552",
    "award_type": "fifthAward",
    "number": "585903"
  },
  {
    "date": "16_7_2552",
    "award_type": "fifthAward",
    "number": "594642"
  },
  {
    "date": "16_7_2552",
    "award_type": "fifthAward",
    "number": "601570"
  },
  {
    "date": "16_7_2552",
    "award_type": "fifthAward",
    "number": "611063"
  },
  {
    "date": "16_7_2552",
    "award_type": "fifthAward",
    "number": "634154"
  },
  {
    "date": "16_7_2552",
    "award_type": "fifthAward",
    "number": "663586"
  },
  {
    "date": "16_7_2552",
    "award_type": "fifthAward",
    "number": "672894"
  },
  {
    "date": "16_7_2552",
    "award_type": "fifthAward",
    "number": "690114"
  },
  {
    "date": "16_7_2552",
    "award_type": "fifthAward",
    "number": "701065"
  },
  {
    "date": "16_7_2552",
    "award_type": "fifthAward",
    "number": "702521"
  },
  {
    "date": "16_7_2552",
    "award_type": "fifthAward",
    "number": "713720"
  },
  {
    "date": "16_7_2552",
    "award_type": "fifthAward",
    "number": "718348"
  },
  {
    "date": "16_7_2552",
    "award_type": "fifthAward",
    "number": "733758"
  },
  {
    "date": "16_7_2552",
    "award_type": "fifthAward",
    "number": "734294"
  },
  {
    "date": "16_7_2552",
    "award_type": "fifthAward",
    "number": "741341"
  },
  {
    "date": "16_7_2552",
    "award_type": "fifthAward",
    "number": "753513"
  },
  {
    "date": "16_7_2552",
    "award_type": "fifthAward",
    "number": "762350"
  },
  {
    "date": "16_7_2552",
    "award_type": "fifthAward",
    "number": "786351"
  },
  {
    "date": "16_7_2552",
    "award_type": "fifthAward",
    "number": "800489"
  },
  {
    "date": "16_7_2552",
    "award_type": "fifthAward",
    "number": "808758"
  },
  {
    "date": "16_7_2552",
    "award_type": "fifthAward",
    "number": "823016"
  },
  {
    "date": "16_7_2552",
    "award_type": "fifthAward",
    "number": "828714"
  },
  {
    "date": "16_7_2552",
    "award_type": "fifthAward",
    "number": "851468"
  },
  {
    "date": "16_7_2552",
    "award_type": "fifthAward",
    "number": "867304"
  },
  {
    "date": "16_7_2552",
    "award_type": "fifthAward",
    "number": "872702"
  },
  {
    "date": "16_7_2552",
    "award_type": "fifthAward",
    "number": "887049"
  },
  {
    "date": "16_7_2552",
    "award_type": "fifthAward",
    "number": "891687"
  },
  {
    "date": "16_7_2552",
    "award_type": "fifthAward",
    "number": "894332"
  },
  {
    "date": "16_7_2552",
    "award_type": "fifthAward",
    "number": "899181"
  },
  {
    "date": "16_7_2552",
    "award_type": "fifthAward",
    "number": "901982"
  },
  {
    "date": "16_7_2552",
    "award_type": "fifthAward",
    "number": "917953"
  },
  {
    "date": "16_7_2552",
    "award_type": "fifthAward",
    "number": "920012"
  },
  {
    "date": "16_7_2552",
    "award_type": "fifthAward",
    "number": "927305"
  },
  {
    "date": "16_7_2552",
    "award_type": "fifthAward",
    "number": "931119"
  },
  {
    "date": "16_7_2552",
    "award_type": "fifthAward",
    "number": "957058"
  },
  {
    "date": "16_7_2552",
    "award_type": "fifthAward",
    "number": "962535"
  },
  {
    "date": "16_7_2552",
    "award_type": "fifthAward",
    "number": "968804"
  }
]