[
  {
    "date": "16_1_2544",
    "award_type": "firstAward",
    "number": "737016"
  },
  {
    "date": "16_1_2544",
    "award_type": "three_prefix",
    "number": ""
  },
  {
    "date": "16_1_2544",
    "award_type": "three_suffix",
    "number": "035"
  },
  {
    "date": "16_1_2544",
    "award_type": "three_suffix",
    "number": "358"
  },
  {
    "date": "16_1_2544",
    "award_type": "three_suffix",
    "number": "515"
  },
  {
    "date": "16_1_2544",
    "award_type": "three_suffix",
    "number": "778"
  },
  {
    "date": "16_1_2544",
    "award_type": "two_suffix",
    "number": "36"
  },
  {
    "date": "16_1_2544",
    "award_type": "secondAward",
    "number": "356497"
  },
  {
    "date": "16_1_2544",
    "award_type": "secondAward",
    "number": "749696"
  },
  {
    "date": "16_1_2544",
    "award_type": "secondAward",
    "number": "761922"
  },
  {
    "date": "16_1_2544",
    "award_type": "secondAward",
    "number": "808057"
  },
  {
    "date": "16_1_2544",
    "award_type": "secondAward",
    "number": "931783"
  },
  {
    "date": "16_1_2544",
    "award_type": "thirdAward",
    "number": "357539"
  },
  {
    "date": "16_1_2544",
    "award_type": "thirdAward",
    "number": "400908"
  },
  {
    "date": "16_1_2544",
    "award_type": "thirdAward",
    "number": "550065"
  },
  {
    "date": "16_1_2544",
    "award_type": "thirdAward",
    "number": "606571"
  },
  {
    "date": "16_1_2544",
    "award_type": "thirdAward",
    "number": "648293"
  },
  {
    "date": "16_1_2544",
    "award_type": "thirdAward",
    "number": "783709"
  },
  {
    "date": "16_1_2544",
    "award_type": "thirdAward",
    "number": "790813"
  },
  {
    "date": "16_1_2544",
    "award_type": "thirdAward",
    "number": "839201"
  },
  {
    "date": "16_1_2544",
    "award_type": "thirdAward",
    "number": "926858"
  },
  {
    "date": "16_1_2544",
    "award_type": "thirdAward",
    "number": "938789"
  },
  {
    "date": "16_1_2544",
    "award_type": "fourthAward",
    "number": "008835"
  },
  {
    "date": "16_1_2544",
    "award_type": "fourthAward",
    "number": "022464"
  },
  {
    "date": "16_1_2544",
    "award_type": "fourthAward",
    "number": "035543"
  },
  {
    "date": "16_1_2544",
    "award_type": "fourthAward",
    "number": "069400"
  },
  {
    "date": "16_1_2544",
    "award_type": "fourthAward",
    "number": "076830"
  },
  {
    "date": "16_1_2544",
    "award_type": "fourthAward",
    "number": "084325"
  },
  {
    "date": "16_1_2544",
    "award_type": "fourthAward",
    "number": "084765"
  },
  {
    "date": "16_1_2544",
    "award_type": "fourthAward",
    "number": "098094"
  },
  {
    "date": "16_1_2544",
    "award_type": "fourthAward",
    "number": "181573"
  },
  {
    "date": "16_1_2544",
    "award_type": "fourthAward",
    "number": "210668"
  },
  {
    "date": "16_1_2544",
    "award_type": "fourthAward",
    "number": "215246"
  },
  {
    "date": "16_1_2544",
    "award_type": "fourthAward",
    "number": "216449"
  },
  {
    "date": "16_1_2544",
    "award_type": "fourthAward",
    "number": "220477"
  },
  {
    "date": "16_1_2544",
    "award_type": "fourthAward",
    "number": "225639"
  },
  {
    "date": "16_1_2544",
    "award_type": "fourthAward",
    "number": "237439"
  },
  {
    "date": "16_1_2544",
    "award_type": "fourthAward",
    "number": "269497"
  },
  {
    "date": "16_1_2544",
    "award_type": "fourthAward",
    "number": "289470"
  },
  {
    "date": "16_1_2544",
    "award_type": "fourthAward",
    "number": "296528"
  },
  {
    "date": "16_1_2544",
    "award_type": "fourthAward",
    "number": "300523"
  },
  {
    "date": "16_1_2544",
    "award_type": "fourthAward",
    "number": "313811"
  },
  {
    "date": "16_1_2544",
    "award_type": "fourthAward",
    "number": "322986"
  },
  {
    "date": "16_1_2544",
    "award_type": "fourthAward",
    "number": "330685"
  },
  {
    "date": "16_1_2544",
    "award_type": "fourthAward",
    "number": "334362"
  },
  {
    "date": "16_1_2544",
    "award_type": "fourthAward",
    "number": "336052"
  },
  {
    "date": "16_1_2544",
    "award_type": "fourthAward",
    "number": "351346"
  },
  {
    "date": "16_1_2544",
    "award_type": "fourthAward",
    "number": "378930"
  },
  {
    "date": "16_1_2544",
    "award_type": "fourthAward",
    "number": "381997"
  },
  {
    "date": "16_1_2544",
    "award_type": "fourthAward",
    "number": "418786"
  },
  {
    "date": "16_1_2544",
    "award_type": "fourthAward",
    "number": "515053"
  },
  {
    "date": "16_1_2544",
    "award_type": "fourthAward",
    "number": "539989"
  },
  {
    "date": "16_1_2544",
    "award_type": "fourthAward",
    "number": "541705"
  },
  {
    "date": "16_1_2544",
    "award_type": "fourthAward",
    "number": "560641"
  },
  {
    "date": "16_1_2544",
    "award_type": "fourthAward",
    "number": "608522"
  },
  {
    "date": "16_1_2544",
    "award_type": "fourthAward",
    "number": "615190"
  },
  {
    "date": "16_1_2544",
    "award_type": "fourthAward",
    "number": "638797"
  },
  {
    "date": "16_1_2544",
    "award_type": "fourthAward",
    "number": "644213"
  },
  {
    "date": "16_1_2544",
    "award_type": "fourthAward",
    "number": "653046"
  },
  {
    "date": "16_1_2544",
    "award_type": "fourthAward",
    "number": "701374"
  },
  {
    "date": "16_1_2544",
    "award_type": "fourthAward",
    "number": "730531"
  },
  {
    "date": "16_1_2544",
    "award_type": "fourthAward",
    "number": "761491"
  },
  {
    "date": "16_1_2544",
    "award_type": "fourthAward",
    "number": "769019"
  },
  {
    "date": "16_1_2544",
    "award_type": "fourthAward",
    "number": "779409"
  },
  {
    "date": "16_1_2544",
    "award_type": "fourthAward",
    "number": "786665"
  },
  {
    "date": "16_1_2544",
    "award_type": "fourthAward",
    "number": "797010"
  },
  {
    "date": "16_1_2544",
    "award_type": "fourthAward",
    "number": "822276"
  },
  {
    "date": "16_1_2544",
    "award_type": "fourthAward",
    "number": "839148"
  },
  {
    "date": "16_1_2544",
    "award_type": "fourthAward",
    "number": "859278"
  },
  {
    "date": "16_1_2544",
    "award_type": "fourthAward",
    "number": "910995"
  },
  {
    "date": "16_1_2544",
    "award_type": "fourthAward",
    "number": "924914"
  },
  {
    "date": "16_1_2544",
    "award_type": "fourthAward",
    "number": "965972"
  },
  {
    "date": "16_1_2544",
    "award_type": "fifthAward",
    "number": "021681"
  },
  {
    "date": "16_1_2544",
    "award_type": "fifthAward",
    "number": "024098"
  },
  {
    "date": "16_1_2544",
    "award_type": "fifthAward",
    "number": "025047"
  },
  {
    "date": "16_1_2544",
    "award_type": "fifthAward",
    "number": "043617"
  },
  {
    "date": "16_1_2544",
    "award_type": "fifthAward",
    "number": "052044"
  },
  {
    "date": "16_1_2544",
    "award_type": "fifthAward",
    "number": "054433"
  },
  {
    "date": "16_1_2544",
    "award_type": "fifthAward",
    "number": "055394"
  },
  {
    "date": "16_1_2544",
    "award_type": "fifthAward",
    "number": "058652"
  },
  {
    "date": "16_1_2544",
    "award_type": "fifthAward",
    "number": "060971"
  },
  {
    "date": "16_1_2544",
    "award_type": "fifthAward",
    "number": "065593"
  },
  {
    "date": "16_1_2544",
    "award_type": "fifthAward",
    "number": "067566"
  },
  {
    "date": "16_1_2544",
    "award_type": "fifthAward",
    "number": "075765"
  },
  {
    "date": "16_1_2544",
    "award_type": "fifthAward",
    "number": "080821"
  },
  {
    "date": "16_1_2544",
    "award_type": "fifthAward",
    "number": "114984"
  },
  {
    "date": "16_1_2544",
    "award_type": "fifthAward",
    "number": "119214"
  },
  {
    "date": "16_1_2544",
    "award_type": "fifthAward",
    "number": "126530"
  },
  {
    "date": "16_1_2544",
    "award_type": "fifthAward",
    "number": "133334"
  },
  {
    "date": "16_1_2544",
    "award_type": "fifthAward",
    "number": "152830"
  },
  {
    "date": "16_1_2544",
    "award_type": "fifthAward",
    "number": "153882"
  },
  {
    "date": "16_1_2544",
    "award_type": "fifthAward",
    "number": "163006"
  },
  {
    "date": "16_1_2544",
    "award_type": "fifthAward",
    "number": "209844"
  },
  {
    "date": "16_1_2544",
    "award_type": "fifthAward",
    "number": "230968"
  },
  {
    "date": "16_1_2544",
    "award_type": "fifthAward",
    "number": "236969"
  },
  {
    "date": "16_1_2544",
    "award_type": "fifthAward",
    "number": "240908"
  },
  {
    "date": "16_1_2544",
    "award_type": "fifthAward",
    "number": "241107"
  },
  {
    "date": "16_1_2544",
    "award_type": "fifthAward",
    "number": "244978"
  },
  {
    "date": "16_1_2544",
    "award_type": "fifthAward",
    "number": "253659"
  },
  {
    "date": "16_1_2544",
    "award_type": "fifthAward",
    "number": "261058"
  },
  {
    "date": "16_1_2544",
    "award_type": "fifthAward",
    "number": "266038"
  },
  {
    "date": "16_1_2544",
    "award_type": "fifthAward",
    "number": "280263"
  },
  {
    "date": "16_1_2544",
    "award_type": "fifthAward",
    "number": "294972"
  },
  {
    "date": "16_1_2544",
    "award_type": "fifthAward",
    "number": "299171"
  },
  {
    "date": "16_1_2544",
    "award_type": "fifthAward",
    "number": "314244"
  },
  {
    "date": "16_1_2544",
    "award_type": "fifthAward",
    "number": "315382"
  },
  {
    "date": "16_1_2544",
    "award_type": "fifthAward",
    "number": "336665"
  },
  {
    "date": "16_1_2544",
    "award_type": "fifthAward",
    "number": "337155"
  },
  {
    "date": "16_1_2544",
    "award_type": "fifthAward",
    "number": "346706"
  },
  {
    "date": "16_1_2544",
    "award_type": "fifthAward",
    "number": "349741"
  },
  {
    "date": "16_1_2544",
    "award_type": "fifthAward",
    "number": "351139"
  },
  {
    "date": "16_1_2544",
    "award_type": "fifthAward",
    "number": "353236"
  },
  {
    "date": "16_1_2544",
    "award_type": "fifthAward",
    "number": "353984"
  },
  {
    "date": "16_1_2544",
    "award_type": "fifthAward",
    "number": "359433"
  },
  {
    "date": "16_1_2544",
    "award_type": "fifthAward",
    "number": "363543"
  },
  {
    "date": "16_1_2544",
    "award_type": "fifthAward",
    "number": "365784"
  },
  {
    "date": "16_1_2544",
    "award_type": "fifthAward",
    "number": "369514"
  },
  {
    "date": "16_1_2544",
    "award_type": "fifthAward",
    "number": "418777"
  },
  {
    "date": "16_1_2544",
    "award_type": "fifthAward",
    "number": "428029"
  },
  {
    "date": "16_1_2544",
    "award_type": "fifthAward",
    "number": "433085"
  },
  {
    "date": "16_1_2544",
    "award_type": "fifthAward",
    "number": "433550"
  },
  {
    "date": "16_1_2544",
    "award_type": "fifthAward",
    "number": "439894"
  },
  {
    "date": "16_1_2544",
    "award_type": "fifthAward",
    "number": "449927"
  },
  {
    "date": "16_1_2544",
    "award_type": "fifthAward",
    "number": "450287"
  },
  {
    "date": "16_1_2544",
    "award_type": "fifthAward",
    "number": "476092"
  },
  {
    "date": "16_1_2544",
    "award_type": "fifthAward",
    "number": "477636"
  },
  {
    "date": "16_1_2544",
    "award_type": "fifthAward",
    "number": "479535"
  },
  {
    "date": "16_1_2544",
    "award_type": "fifthAward",
    "number": "499931"
  },
  {
    "date": "16_1_2544",
    "award_type": "fifthAward",
    "number": "504788"
  },
  {
    "date": "16_1_2544",
    "award_type": "fifthAward",
    "number": "526833"
  },
  {
    "date": "16_1_2544",
    "award_type": "fifthAward",
    "number": "526955"
  },
  {
    "date": "16_1_2544",
    "award_type": "fifthAward",
    "number": "551061"
  },
  {
    "date": "16_1_2544",
    "award_type": "fifthAward",
    "number": "571541"
  },
  {
    "date": "16_1_2544",
    "award_type": "fifthAward",
    "number": "627640"
  },
  {
    "date": "16_1_2544",
    "award_type": "fifthAward",
    "number": "634264"
  },
  {
    "date": "16_1_2544",
    "award_type": "fifthAward",
    "number": "660938"
  },
  {
    "date": "16_1_2544",
    "award_type": "fifthAward",
    "number": "667691"
  },
  {
    "date": "16_1_2544",
    "award_type": "fifthAward",
    "number": "673484"
  },
  {
    "date": "16_1_2544",
    "award_type": "fifthAward",
    "number": "678264"
  },
  {
    "date": "16_1_2544",
    "award_type": "fifthAward",
    "number": "686211"
  },
  {
    "date": "16_1_2544",
    "award_type": "fifthAward",
    "number": "700041"
  },
  {
    "date": "16_1_2544",
    "award_type": "fifthAward",
    "number": "707002"
  },
  {
    "date": "16_1_2544",
    "award_type": "fifthAward",
    "number": "714011"
  },
  {
    "date": "16_1_2544",
    "award_type": "fifthAward",
    "number": "716663"
  },
  {
    "date": "16_1_2544",
    "award_type": "fifthAward",
    "number": "718057"
  },
  {
    "date": "16_1_2544",
    "award_type": "fifthAward",
    "number": "719110"
  },
  {
    "date": "16_1_2544",
    "award_type": "fifthAward",
    "number": "726694"
  },
  {
    "date": "16_1_2544",
    "award_type": "fifthAward",
    "number": "741802"
  },
  {
    "date": "16_1_2544",
    "award_type": "fifthAward",
    "number": "742502"
  },
  {
    "date": "16_1_2544",
    "award_type": "fifthAward",
    "number": "742727"
  },
  {
    "date": "16_1_2544",
    "award_type": "fifthAward",
    "number": "770174"
  },
  {
    "date": "16_1_2544",
    "award_type": "fifthAward",
    "number": "770813"
  },
  {
    "date": "16_1_2544",
    "award_type": "fifthAward",
    "number": "775989"
  },
  {
    "date": "16_1_2544",
    "award_type": "fifthAward",
    "number": "778309"
  },
  {
    "date": "16_1_2544",
    "award_type": "fifthAward",
    "number": "791817"
  },
  {
    "date": "16_1_2544",
    "award_type": "fifthAward",
    "number": "794274"
  },
  {
    "date": "16_1_2544",
    "award_type": "fifthAward",
    "number": "795573"
  },
  {
    "date": "16_1_2544",
    "award_type": "fifthAward",
    "number": "829809"
  },
  {
    "date": "16_1_2544",
    "award_type": "fifthAward",
    "number": "831288"
  },
  {
    "date": "16_1_2544",
    "award_type": "fifthAward",
    "number": "840161"
  },
  {
    "date": "16_1_2544",
    "award_type": "fifthAward",
    "number": "847617"
  },
  {
    "date": "16_1_2544",
    "award_type": "fifthAward",
    "number": "849778"
  },
  {
    "date": "16_1_2544",
    "award_type": "fifthAward",
    "number": "851619"
  },
  {
    "date": "16_1_2544",
    "award_type": "fifthAward",
    "number": "852010"
  },
  {
    "date": "16_1_2544",
    "award_type": "fifthAward",
    "number": "891987"
  },
  {
    "date": "16_1_2544",
    "award_type": "fifthAward",
    "number": "940920"
  },
  {
    "date": "16_1_2544",
    "award_type": "fifthAward",
    "number": "946630"
  },
  {
    "date": "16_1_2544",
    "award_type": "fifthAward",
    "number": "958257"
  },
  {
    "date": "16_1_2544",
    "award_type": "fifthAward",
    "number": "964143"
  },
  {
    "date": "16_1_2544",
    "award_type": "fifthAward",
    "number": "977944"
  },
  {
    "date": "16_1_2544",
    "award_type": "fifthAward",
    "number": "986535"
  },
  {
    "date": "16_1_2544",
    "award_type": "fifthAward",
    "number": "992405"
  }
]