[
  {
    "date": "16_1_2543",
    "award_type": "firstAward",
    "number": "442183"
  },
  {
    "date": "16_1_2543",
    "award_type": "three_prefix",
    "number": ""
  },
  {
    "date": "16_1_2543",
    "award_type": "three_suffix",
    "number": "269"
  },
  {
    "date": "16_1_2543",
    "award_type": "three_suffix",
    "number": "540"
  },
  {
    "date": "16_1_2543",
    "award_type": "three_suffix",
    "number": "847"
  },
  {
    "date": "16_1_2543",
    "award_type": "three_suffix",
    "number": "950"
  },
  {
    "date": "16_1_2543",
    "award_type": "two_suffix",
    "number": "82"
  }
]